{
	"animations": [
		{
			"offsets": [
				-150,
				-250
			],
			"indices": [],
			"fps": 20,
			"anim": "singLEFT",
			"loop": false,
			"name": "BOYFRIEND left"
		},
		{
			"offsets": [
				-150,
				-250
			],
			"indices": [],
			"fps": 20,
			"anim": "singDOWN",
			"loop": false,
			"name": "BOYFRIEND down"
		},
		{
			"offsets": [
				-150,
				-200
			],
			"indices": [],
			"fps": 20,
			"anim": "singUP",
			"loop": false,
			"name": "BOYFRIEND up"
		},
		{
			"offsets": [
				-150,
				-250
			],
			"indices": [],
			"fps": 20,
			"anim": "singRIGHT",
			"loop": false,
			"name": "BOYFRIEND right"
		},
		{
			"offsets": [
				-150,
				-250
			],
			"indices": [],
			"fps": 8,
			"anim": "idle",
			"loop": false,
			"name": "BOYFRIEND idle"
		}
	],
	"no_antialiasing": true,
	"image": "characters/BOYFRIEND",
	"position": [
		0,
		0
	],
	"healthicon": "face",
	"flip_x": true,
	"healthbar_colors": [
		161,
		161,
		161
	],
	"camera_position": [
		0,
		230
	],
	"sing_duration": 6.1,
	"scale": 1.2
}